verity/__init__.py
verity/__version__.py
verity/json.py
verity-0.1.dist-info/DESCRIPTION.rst
verity-0.1.dist-info/METADATA
verity-0.1.dist-info/RECORD
verity-0.1.dist-info/WHEEL
verity-0.1.dist-info/metadata.json
verity-0.1.dist-info/top_level.txt
