Metadata-Version: 2.0
Name: verity
Version: 0.1
Summary: Simple way to validate/cast incoming JSON data.
Home-page: https://github.com/funkybob/verity
Author: Curtis Maloney
Author-email: curtis@tinbrain.net
License: MIT
Platform: UNKNOWN
Classifier: License :: OSI Approved :: MIT License
Classifier: Programming Language :: Python
Classifier: Programming Language :: Python :: 3
Classifier: Programming Language :: Python :: 3.3
Classifier: Programming Language :: Python :: 3.4
Classifier: Programming Language :: Python :: 3.5
Classifier: Programming Language :: Python :: 3.6
Classifier: Programming Language :: Python :: Implementation :: CPython
Classifier: Programming Language :: Python :: Implementation :: PyPy
